[
null,
{"id":1,"battlerName":"hzj","characterIndex":0,"characterName":"hzj","classId":9,"equips":[51,145,0,0,0],"faceIndex":0,"faceName":"hzj","traits":[],"initialLevel":1,"maxLevel":31,"name":"胡子鉴","nickname":"意志的信徒","note":"","profile":"可以使用魔法，但原理是什么呢？魔力回复增加"},
{"id":2,"battlerName":"pjt","characterIndex":0,"characterName":"pjt","classId":10,"equips":[52,0,0,0,0],"faceIndex":0,"faceName":"pjt","traits":[],"initialLevel":1,"maxLevel":31,"name":"浦金涛","nickname":"狂热的战士","note":"","profile":"想要一刀决定胜负。暴击率增加"},
{"id":3,"battlerName":"hf","characterIndex":0,"characterName":"hf","classId":11,"equips":[53,0,0,0,0],"faceIndex":0,"faceName":"hf","traits":[],"initialLevel":1,"maxLevel":31,"name":"韩放","nickname":"勤恳的电工","note":"","profile":"想学习电工基础和中医基础，这样才能保护队友。受击率增加，\n暴击回避增加"},
{"id":4,"battlerName":"hxy","characterIndex":0,"characterName":"hxy","classId":12,"equips":[54,0,0,0,0],"faceIndex":0,"faceName":"hxy","traits":[],"initialLevel":1,"maxLevel":31,"name":"何欣宇","nickname":"重火力爱好者","note":"","profile":"想要最强大的火力。TP回复增加"},
{"id":5,"battlerName":"csk","characterIndex":0,"characterName":"csk","classId":13,"equips":[55,0,0,0,0],"faceIndex":0,"faceName":"csk","traits":[],"initialLevel":1,"maxLevel":31,"name":"陈少康","nickname":"天才战术家","note":"","profile":"想要自己卓越的战术规划得到发挥。有概率反击敌人"},
{"id":6,"battlerName":"sv_fantasy-heroine-girl butterfly girl","characterIndex":0,"characterName":"$fantasy-heroine-girl butterfly girl","classId":14,"equips":[56,0,0,0,0,0],"faceIndex":4,"faceName":"fantasy-heroine-girl butterfly girl","traits":[],"initialLevel":1,"maxLevel":31,"name":"王雨宸","nickname":"陈少康的后援","note":"","profile":"想要在后排支援队友。普攻有概率附加脆弱"},
{"id":7,"battlerName":"qgc","characterIndex":0,"characterName":"qgc","classId":15,"equips":[57,0,0,0,0],"faceIndex":0,"faceName":"qgc","traits":[],"initialLevel":1,"maxLevel":31,"name":"瞿高丞","nickname":"火焰狙击手","note":"","profile":"想通过控制火焰来进行狙击和支援。命中率变为十倍"},
{"id":8,"battlerName":"jj1","characterIndex":0,"characterName":"jj1","classId":17,"equips":[54,0,0,0,0],"faceIndex":0,"faceName":"jj1","traits":[],"initialLevel":69,"maxLevel":99,"name":"机甲一号","nickname":"幻想中的人形机甲","note":"","profile":"韩放制造的机甲，特点是中庸的属性。无法被治疗，免疫控制"},
{"id":9,"battlerName":"yrj","characterIndex":0,"characterName":"yrj","classId":20,"equips":[67,0,0,0,0],"faceIndex":0,"faceName":"yrj","traits":[],"initialLevel":1,"maxLevel":31,"name":"杨锐杰","nickname":"魔法眷顾的刺客","note":"","profile":"想要成为最强的刺客。有概率额外获得一回合"},
{"id":10,"battlerName":"yyf","characterIndex":0,"characterName":"yyf","classId":16,"equips":[71,0,0,0,0],"faceIndex":0,"faceName":"yyf","traits":[],"initialLevel":1,"maxLevel":31,"name":"杨亦凡","nickname":"故事叙述者","note":"","profile":"想要成为必不可少的辅助。无法被削弱防御力"},
{"id":11,"battlerName":"hmhzj","characterIndex":0,"characterName":"hmhzj","classId":21,"equips":[0,0,0,0,0],"faceIndex":0,"faceName":"hmhzj","traits":[],"initialLevel":81,"maxLevel":81,"name":"黑暗虚影","nickname":"纯粹混沌的造物","note":"","profile":"黑暗中的影子"},
{"id":12,"battlerName":"fyc","characterIndex":0,"characterName":"fyc","classId":22,"equips":[60,0,0,0,0],"faceIndex":0,"faceName":"fyc","traits":[],"initialLevel":1,"maxLevel":31,"name":"冯轶辰","nickname":"不留情的猎手","note":"","profile":"想要爆发不一般的能力。在不爆发时可以快速恢复生命值，获\n得一个可以复制技能的傀儡"},
{"id":13,"battlerName":"Package3_7_mvt","characterIndex":6,"characterName":"Package3_mvt","classId":23,"equips":[60,0,0,0,0],"faceIndex":6,"faceName":"Package3_mvt","traits":[],"initialLevel":1,"maxLevel":31,"name":"傀儡","nickname":"神奇的玩偶","note":"","profile":"每当冯轶辰释放一个技能，复制该技能"},
{"id":14,"battlerName":"wh","characterIndex":0,"characterName":"wh","classId":24,"equips":[86,0,0,0,0],"faceIndex":0,"faceName":"wh","traits":[],"initialLevel":1,"maxLevel":31,"name":"王翚","nickname":"孤高的骑士","note":"","profile":"正在寻找他的公主。获得10%物理免伤"},
{"id":15,"battlerName":"","characterIndex":0,"characterName":"","classId":1,"equips":[0,0,0,0,0],"faceIndex":0,"faceName":"","traits":[],"initialLevel":1,"maxLevel":99,"name":"","nickname":"","note":"","profile":""}
]